element_event/__init__.py
element_event/event.py
element_event/trial.py
element_event/version.py
element_event-0.2.3.dist-info/LICENSE
element_event-0.2.3.dist-info/METADATA
element_event-0.2.3.dist-info/WHEEL
element_event-0.2.3.dist-info/top_level.txt
element_event-0.2.3.dist-info/RECORD
