Metadata-Version: 2.1
Name: element-event
Version: 0.2.3
Summary: DataJoint Elements for Trialized Experiments
Home-page: https://github.com/datajoint/element-event
Author: DataJoint
Author-email: info@datajoint.com
License: MIT
Keywords: neuroscience behavior bpod trials datajoint
Platform: UNKNOWN
License-File: LICENSE
Requires-Dist: datajoint (>=0.13)
